{".class":"MypyFile","_fullname":"ai_core.module_registry","future_import_flags":[],"is_partial_stub_package":false,"is_stub":false,"names":{".class":"SymbolTable","Any":{".class":"SymbolTableNode","cross_ref":"typing.Any","kind":"Gdef","module_hidden":true,"module_public":false},"Callable":{".class":"SymbolTableNode","cross_ref":"typing.Callable","kind":"Gdef","module_hidden":true,"module_public":false},"ConfigManager":{".class":"SymbolTableNode","kind":"Gdef","node":{".class":"TypeInfo","_promote":[],"abstract_attributes":[],"alt_promote":null,"bases":["builtins.object"],"dataclass_transform_spec":null,"declared_metaclass":null,"defn":{".class":"ClassDef","fullname":"ai_core.module_registry.ConfigManager","name":"ConfigManager","type_vars":[]},"deletable_attributes":[],"deprecated":null,"flags":[],"fullname":"ai_core.module_registry.ConfigManager","has_param_spec_type":false,"metaclass_type":null,"metadata":{},"module_name":"ai_core.module_registry","mro":["ai_core.module_registry.ConfigManager","builtins.object"],"names":{".class":"SymbolTable","__init__":{".class":"SymbolTableNode","kind":"Mdef","node":{".class":"FuncDef","abstract_status":0,"arg_kinds":[0,0],"arg_names":["self","config_path"],"dataclass_transform_spec":null,"deprecated":null,"flags":[],"fullname":"ai_core.module_registry.ConfigManager.__init__","name":"__init__","type":{".class":"CallableType","arg_kinds":[0,0],"arg_names":["self","config_path"],"arg_types":["ai_core.module_registry.ConfigManager","builtins.str"],"bound_args":[],"def_extras":{"first_arg":"self"},"fallback":"builtins.function","from_concatenate":false,"implicit":false,"imprecise_arg_kinds":false,"is_ellipsis_args":false,"name":"__init__ of ConfigManager","ret_type":{".class":"NoneType"},"type_guard":null,"type_is":null,"unpack_kwargs":false,"variables":[]}}},"config_path":{".class":"SymbolTableNode","implicit":true,"kind":"Mdef","node":{".class":"Var","flags":["is_inferred"],"fullname":"ai_core.module_registry.ConfigManager.config_path","name":"config_path","type":"builtins.str"}},"load_configuration":{".class":"SymbolTableNode","kind":"Mdef","node":{".class":"FuncDef","abstract_status":0,"arg_kinds":[0],"arg_names":["self"],"dataclass_transform_spec":null,"deprecated":null,"flags":["is_coroutine"],"fullname":"ai_core.module_registry.ConfigManager.load_configuration","name":"load_configuration","type":{".class":"CallableType","arg_kinds":[0],"arg_names":["self"],"arg_types":["ai_core.module_registry.ConfigManager"],"bound_args":[],"def_extras":{"first_arg":"self"},"fallback":"builtins.function","from_concatenate":false,"implicit":false,"imprecise_arg_kinds":false,"is_ellipsis_args":false,"name":"load_configuration of ConfigManager","ret_type":{".class":"Instance","args":[{".class":"AnyType","missing_import_name":null,"source_any":null,"type_of_any":6},{".class":"AnyType","missing_import_name":null,"source_any":null,"type_of_any":6},{".class":"TypeAliasType","args":[],"type_ref":"ai_core.module_registry.ModulesDict"}],"extra_attrs":null,"type_ref":"typing.Coroutine"},"type_guard":null,"type_is":null,"unpack_kwargs":false,"variables":[]}}},"save_configuration":{".class":"SymbolTableNode","kind":"Mdef","node":{".class":"FuncDef","abstract_status":0,"arg_kinds":[0,0],"arg_names":["self","modules"],"dataclass_transform_spec":null,"deprecated":null,"flags":["is_coroutine"],"fullname":"ai_core.module_registry.ConfigManager.save_configuration","name":"save_configuration","type":{".class":"CallableType","arg_kinds":[0,0],"arg_names":["self","modules"],"arg_types":["ai_core.module_registry.ConfigManager",{".class":"Instance","args":["builtins.str",{".class":"TypeAliasType","args":[],"type_ref":"ai_core.module_registry.ModuleConfig"}],"extra_attrs":null,"type_ref":"builtins.dict"}],"bound_args":[],"def_extras":{"first_arg":"self"},"fallback":"builtins.function","from_concatenate":false,"implicit":false,"imprecise_arg_kinds":false,"is_ellipsis_args":false,"name":"save_configuration of ConfigManager","ret_type":{".class":"Instance","args":[{".class":"AnyType","missing_import_name":null,"source_any":null,"type_of_any":6},{".class":"AnyType","missing_import_name":null,"source_any":null,"type_of_any":6},{".class":"NoneType"}],"extra_attrs":null,"type_ref":"typing.Coroutine"},"type_guard":null,"type_is":null,"unpack_kwargs":false,"variables":[]}}}},"self_type":{".class":"TypeVarType","default":{".class":"AnyType","missing_import_name":null,"source_any":null,"type_of_any":4},"fullname":"ai_core.module_registry.ConfigManager.Self","id":0,"name":"Self","namespace":"","upper_bound":"ai_core.module_registry.ConfigManager","values":[],"variance":0},"slots":null,"tuple_type":null,"type_vars":[],"typeddict_type":null}},"DependencyResolver":{".class":"SymbolTableNode","kind":"Gdef","node":{".class":"TypeInfo","_promote":[],"abstract_attributes":[],"alt_promote":null,"bases":["builtins.object"],"dataclass_transform_spec":null,"declared_metaclass":null,"defn":{".class":"ClassDef","fullname":"ai_core.module_registry.DependencyResolver","name":"DependencyResolver","type_vars":[]},"deletable_attributes":[],"deprecated":null,"flags":[],"fullname":"ai_core.module_registry.DependencyResolver","has_param_spec_type":false,"metaclass_type":null,"metadata":{},"module_name":"ai_core.module_registry","mro":["ai_core.module_registry.DependencyResolver","builtins.object"],"names":{".class":"SymbolTable","__init__":{".class":"SymbolTableNode","kind":"Mdef","node":{".class":"FuncDef","abstract_status":0,"arg_kinds":[0,0,0],"arg_names":["self","modules","dependencies"],"dataclass_transform_spec":null,"deprecated":null,"flags":[],"fullname":"ai_core.module_registry.DependencyResolver.__init__","name":"__init__","type":{".class":"CallableType","arg_kinds":[0,0,0],"arg_names":["self","modules","dependencies"],"arg_types":["ai_core.module_registry.DependencyResolver",{".class":"Instance","args":["builtins.str",{".class":"AnyType","missing_import_name":null,"source_any":null,"type_of_any":2}],"extra_attrs":null,"type_ref":"builtins.dict"},{".class":"Instance","args":["builtins.str",{".class":"Instance","args":["builtins.str"],"extra_attrs":null,"type_ref":"builtins.list"}],"extra_attrs":null,"type_ref":"builtins.dict"}],"bound_args":[],"def_extras":{"first_arg":"self"},"fallback":"builtins.function","from_concatenate":false,"implicit":false,"imprecise_arg_kinds":false,"is_ellipsis_args":false,"name":"__init__ of DependencyResolver","ret_type":{".class":"NoneType"},"type_guard":null,"type_is":null,"unpack_kwargs":false,"variables":[]}}},"compute_startup_order":{".class":"SymbolTableNode","kind":"Mdef","node":{".class":"FuncDef","abstract_status":0,"arg_kinds":[0],"arg_names":["self"],"dataclass_transform_spec":null,"deprecated":null,"flags":[],"fullname":"ai_core.module_registry.DependencyResolver.compute_startup_order","name":"compute_startup_order","type":{".class":"CallableType","arg_kinds":[0],"arg_names":["self"],"arg_types":["ai_core.module_registry.DependencyResolver"],"bound_args":[],"def_extras":{"first_arg":"self"},"fallback":"builtins.function","from_concatenate":false,"implicit":false,"imprecise_arg_kinds":false,"is_ellipsis_args":false,"name":"compute_startup_order of DependencyResolver","ret_type":{".class":"Instance","args":["builtins.str"],"extra_attrs":null,"type_ref":"builtins.list"},"type_guard":null,"type_is":null,"unpack_kwargs":false,"variables":[]}}},"dependencies":{".class":"SymbolTableNode","implicit":true,"kind":"Mdef","node":{".class":"Var","flags":["is_inferred"],"fullname":"ai_core.module_registry.DependencyResolver.dependencies","name":"dependencies","type":{".class":"Instance","args":["builtins.str",{".class":"Instance","args":["builtins.str"],"extra_attrs":null,"type_ref":"builtins.list"}],"extra_attrs":null,"type_ref":"builtins.dict"}}},"modules":{".class":"SymbolTableNode","implicit":true,"kind":"Mdef","node":{".class":"Var","flags":["is_inferred"],"fullname":"ai_core.module_registry.DependencyResolver.modules","name":"modules","type":{".class":"Instance","args":["builtins.str",{".class":"AnyType","missing_import_name":null,"source_any":null,"type_of_any":2}],"extra_attrs":null,"type_ref":"builtins.dict"}}},"startup_order":{".class":"SymbolTableNode","implicit":true,"kind":"Mdef","node":{".class":"Var","flags":["explicit_self_type","is_ready","is_inferred"],"fullname":"ai_core.module_registry.DependencyResolver.startup_order","name":"startup_order","type":{".class":"Instance","args":["builtins.str"],"extra_attrs":null,"type_ref":"builtins.list"}}}},"self_type":{".class":"TypeVarType","default":{".class":"AnyType","missing_import_name":null,"source_any":null,"type_of_any":4},"fullname":"ai_core.module_registry.DependencyResolver.Self","id":0,"name":"Self","namespace":"","upper_bound":"ai_core.module_registry.DependencyResolver","values":[],"variance":0},"slots":null,"tuple_type":null,"type_vars":[],"typeddict_type":null}},"Dict":{".class":"SymbolTableNode","cross_ref":"typing.Dict","kind":"Gdef","module_hidden":true,"module_public":false},"LifecycleManager":{".class":"SymbolTableNode","kind":"Gdef","node":{".class":"TypeInfo","_promote":[],"abstract_attributes":[],"alt_promote":null,"bases":["builtins.object"],"dataclass_transform_spec":null,"declared_metaclass":null,"defn":{".class":"ClassDef","fullname":"ai_core.module_registry.LifecycleManager","name":"LifecycleManager","type_vars":[]},"deletable_attributes":[],"deprecated":null,"flags":[],"fullname":"ai_core.module_registry.LifecycleManager","has_param_spec_type":false,"metaclass_type":null,"metadata":{},"module_name":"ai_core.module_registry","mro":["ai_core.module_registry.LifecycleManager","builtins.object"],"names":{".class":"SymbolTable","__init__":{".class":"SymbolTableNode","kind":"Mdef","node":{".class":"FuncDef","abstract_status":0,"arg_kinds":[0,0,0],"arg_names":["self","modules","startup_order"],"dataclass_transform_spec":null,"deprecated":null,"flags":[],"fullname":"ai_core.module_registry.LifecycleManager.__init__","name":"__init__","type":{".class":"CallableType","arg_kinds":[0,0,0],"arg_names":["self","modules","startup_order"],"arg_types":["ai_core.module_registry.LifecycleManager",{".class":"Instance","args":["builtins.str",{".class":"AnyType","missing_import_name":null,"source_any":null,"type_of_any":2}],"extra_attrs":null,"type_ref":"builtins.dict"},{".class":"Instance","args":["builtins.str"],"extra_attrs":null,"type_ref":"builtins.list"}],"bound_args":[],"def_extras":{"first_arg":"self"},"fallback":"builtins.function","from_concatenate":false,"implicit":false,"imprecise_arg_kinds":false,"is_ellipsis_args":false,"name":"__init__ of LifecycleManager","ret_type":{".class":"NoneType"},"type_guard":null,"type_is":null,"unpack_kwargs":false,"variables":[]}}},"initialize_modules":{".class":"SymbolTableNode","kind":"Mdef","node":{".class":"FuncDef","abstract_status":0,"arg_kinds":[0],"arg_names":["self"],"dataclass_transform_spec":null,"deprecated":null,"flags":["is_coroutine"],"fullname":"ai_core.module_registry.LifecycleManager.initialize_modules","name":"initialize_modules","type":null}},"is_initialized":{".class":"SymbolTableNode","implicit":true,"kind":"Mdef","node":{".class":"Var","flags":["is_inferred"],"fullname":"ai_core.module_registry.LifecycleManager.is_initialized","name":"is_initialized","type":"builtins.bool"}},"modules":{".class":"SymbolTableNode","implicit":true,"kind":"Mdef","node":{".class":"Var","flags":["is_inferred"],"fullname":"ai_core.module_registry.LifecycleManager.modules","name":"modules","type":{".class":"Instance","args":["builtins.str",{".class":"AnyType","missing_import_name":null,"source_any":null,"type_of_any":2}],"extra_attrs":null,"type_ref":"builtins.dict"}}},"shutdown_modules":{".class":"SymbolTableNode","kind":"Mdef","node":{".class":"FuncDef","abstract_status":0,"arg_kinds":[0],"arg_names":["self"],"dataclass_transform_spec":null,"deprecated":null,"flags":["is_coroutine"],"fullname":"ai_core.module_registry.LifecycleManager.shutdown_modules","name":"shutdown_modules","type":null}},"startup_order":{".class":"SymbolTableNode","implicit":true,"kind":"Mdef","node":{".class":"Var","flags":["is_inferred"],"fullname":"ai_core.module_registry.LifecycleManager.startup_order","name":"startup_order","type":{".class":"Instance","args":["builtins.str"],"extra_attrs":null,"type_ref":"builtins.list"}}}},"self_type":{".class":"TypeVarType","default":{".class":"AnyType","missing_import_name":null,"source_any":null,"type_of_any":4},"fullname":"ai_core.module_registry.LifecycleManager.Self","id":0,"name":"Self","namespace":"","upper_bound":"ai_core.module_registry.LifecycleManager","values":[],"variance":0},"slots":null,"tuple_type":null,"type_vars":[],"typeddict_type":null}},"List":{".class":"SymbolTableNode","cross_ref":"typing.List","kind":"Gdef","module_hidden":true,"module_public":false},"MetricsTracker":{".class":"SymbolTableNode","kind":"Gdef","node":{".class":"TypeInfo","_promote":[],"abstract_attributes":[],"alt_promote":null,"bases":["builtins.object"],"dataclass_transform_spec":null,"declared_metaclass":null,"defn":{".class":"ClassDef","fullname":"ai_core.module_registry.MetricsTracker","name":"MetricsTracker","type_vars":[]},"deletable_attributes":[],"deprecated":null,"flags":[],"fullname":"ai_core.module_registry.MetricsTracker","has_param_spec_type":false,"metaclass_type":null,"metadata":{},"module_name":"ai_core.module_registry","mro":["ai_core.module_registry.MetricsTracker","builtins.object"],"names":{".class":"SymbolTable","__init__":{".class":"SymbolTableNode","kind":"Mdef","node":{".class":"FuncDef","abstract_status":0,"arg_kinds":[0,0,0,0],"arg_names":["self","modules","resource_manager","metrics_collector"],"dataclass_transform_spec":null,"deprecated":null,"flags":[],"fullname":"ai_core.module_registry.MetricsTracker.__init__","name":"__init__","type":{".class":"CallableType","arg_kinds":[0,0,0,0],"arg_names":["self","modules","resource_manager","metrics_collector"],"arg_types":["ai_core.module_registry.MetricsTracker",{".class":"Instance","args":["builtins.str",{".class":"AnyType","missing_import_name":null,"source_any":null,"type_of_any":2}],"extra_attrs":null,"type_ref":"builtins.dict"},{".class":"UnionType","items":["ai_core.resource_management.ResourceManager",{".class":"NoneType"}],"uses_pep604_syntax":false},{".class":"AnyType","missing_import_name":null,"source_any":null,"type_of_any":2}],"bound_args":[],"def_extras":{"first_arg":"self"},"fallback":"builtins.function","from_concatenate":false,"implicit":false,"imprecise_arg_kinds":false,"is_ellipsis_args":false,"name":"__init__ of MetricsTracker","ret_type":{".class":"NoneType"},"type_guard":null,"type_is":null,"unpack_kwargs":false,"variables":[]}}},"metrics_collector":{".class":"SymbolTableNode","implicit":true,"kind":"Mdef","node":{".class":"Var","flags":["is_inferred"],"fullname":"ai_core.module_registry.MetricsTracker.metrics_collector","name":"metrics_collector","type":{".class":"AnyType","missing_import_name":null,"source_any":null,"type_of_any":2}}},"modules":{".class":"SymbolTableNode","implicit":true,"kind":"Mdef","node":{".class":"Var","flags":["is_inferred"],"fullname":"ai_core.module_registry.MetricsTracker.modules","name":"modules","type":{".class":"Instance","args":["builtins.str",{".class":"AnyType","missing_import_name":null,"source_any":null,"type_of_any":2}],"extra_attrs":null,"type_ref":"builtins.dict"}}},"resource_manager":{".class":"SymbolTableNode","implicit":true,"kind":"Mdef","node":{".class":"Var","flags":["is_inferred"],"fullname":"ai_core.module_registry.MetricsTracker.resource_manager","name":"resource_manager","type":{".class":"UnionType","items":["ai_core.resource_management.ResourceManager",{".class":"NoneType"}],"uses_pep604_syntax":false}}},"track_registration":{".class":"SymbolTableNode","kind":"Mdef","node":{".class":"FuncDef","abstract_status":0,"arg_kinds":[0,0,0],"arg_names":["self","module_id","module_class"],"dataclass_transform_spec":null,"deprecated":null,"flags":["is_coroutine"],"fullname":"ai_core.module_registry.MetricsTracker.track_registration","name":"track_registration","type":{".class":"CallableType","arg_kinds":[0,0,0],"arg_names":["self","module_id","module_class"],"arg_types":["ai_core.module_registry.MetricsTracker","builtins.str",{".class":"TypeType","item":{".class":"AnyType","missing_import_name":null,"source_any":null,"type_of_any":5}}],"bound_args":[],"def_extras":{"first_arg":"self"},"fallback":"builtins.function","from_concatenate":false,"implicit":false,"imprecise_arg_kinds":false,"is_ellipsis_args":false,"name":"track_registration of MetricsTracker","ret_type":{".class":"Instance","args":[{".class":"AnyType","missing_import_name":null,"source_any":null,"type_of_any":6},{".class":"AnyType","missing_import_name":null,"source_any":null,"type_of_any":6},{".class":"NoneType"}],"extra_attrs":null,"type_ref":"typing.Coroutine"},"type_guard":null,"type_is":null,"unpack_kwargs":false,"variables":[]}}},"track_shutdown":{".class":"SymbolTableNode","kind":"Mdef","node":{".class":"FuncDef","abstract_status":0,"arg_kinds":[0],"arg_names":["self"],"dataclass_transform_spec":null,"deprecated":null,"flags":["is_coroutine"],"fullname":"ai_core.module_registry.MetricsTracker.track_shutdown","name":"track_shutdown","type":{".class":"CallableType","arg_kinds":[0],"arg_names":["self"],"arg_types":["ai_core.module_registry.MetricsTracker"],"bound_args":[],"def_extras":{"first_arg":"self"},"fallback":"builtins.function","from_concatenate":false,"implicit":false,"imprecise_arg_kinds":false,"is_ellipsis_args":false,"name":"track_shutdown of MetricsTracker","ret_type":{".class":"Instance","args":[{".class":"AnyType","missing_import_name":null,"source_any":null,"type_of_any":6},{".class":"AnyType","missing_import_name":null,"source_any":null,"type_of_any":6},{".class":"NoneType"}],"extra_attrs":null,"type_ref":"typing.Coroutine"},"type_guard":null,"type_is":null,"unpack_kwargs":false,"variables":[]}}},"track_status_change":{".class":"SymbolTableNode","kind":"Mdef","node":{".class":"FuncDef","abstract_status":0,"arg_kinds":[0,0,0],"arg_names":["self","module_id","status"],"dataclass_transform_spec":null,"deprecated":null,"flags":["is_coroutine"],"fullname":"ai_core.module_registry.MetricsTracker.track_status_change","name":"track_status_change","type":{".class":"CallableType","arg_kinds":[0,0,0],"arg_names":["self","module_id","status"],"arg_types":["ai_core.module_registry.MetricsTracker","builtins.str","builtins.str"],"bound_args":[],"def_extras":{"first_arg":"self"},"fallback":"builtins.function","from_concatenate":false,"implicit":false,"imprecise_arg_kinds":false,"is_ellipsis_args":false,"name":"track_status_change of MetricsTracker","ret_type":{".class":"Instance","args":[{".class":"AnyType","missing_import_name":null,"source_any":null,"type_of_any":6},{".class":"AnyType","missing_import_name":null,"source_any":null,"type_of_any":6},{".class":"NoneType"}],"extra_attrs":null,"type_ref":"typing.Coroutine"},"type_guard":null,"type_is":null,"unpack_kwargs":false,"variables":[]}}}},"self_type":{".class":"TypeVarType","default":{".class":"AnyType","missing_import_name":null,"source_any":null,"type_of_any":4},"fullname":"ai_core.module_registry.MetricsTracker.Self","id":0,"name":"Self","namespace":"","upper_bound":"ai_core.module_registry.MetricsTracker","values":[],"variance":0},"slots":null,"tuple_type":null,"type_vars":[],"typeddict_type":null}},"ModuleConfig":{".class":"SymbolTableNode","kind":"Gdef","node":{".class":"TypeInfo","_promote":[],"abstract_attributes":[],"alt_promote":null,"bases":["typing._TypedDict"],"dataclass_transform_spec":null,"declared_metaclass":null,"defn":{".class":"ClassDef","fullname":"ai_core.module_registry.ModuleConfig","name":"ModuleConfig","type_vars":[]},"deletable_attributes":[],"deprecated":null,"flags":[],"fullname":"ai_core.module_registry.ModuleConfig","has_param_spec_type":false,"metaclass_type":null,"metadata":{},"module_name":"ai_core.module_registry","mro":["ai_core.module_registry.ModuleConfig","typing._TypedDict","typing.Mapping","typing.Collection","typing.Iterable","typing.Container","builtins.object"],"names":{".class":"SymbolTable"},"self_type":null,"slots":null,"tuple_type":null,"type_vars":[],"typeddict_type":{".class":"TypedDictType","fallback":"typing._TypedDict","items":[["class_name","builtins.str"],["module_name","builtins.str"],["config",{".class":"Instance","args":["builtins.str",{".class":"AnyType","missing_import_name":null,"source_any":null,"type_of_any":2}],"extra_attrs":null,"type_ref":"builtins.dict"}],["status","builtins.str"],["registered_time","builtins.float"],["last_status_update","builtins.float"],["dependencies",{".class":"Instance","args":["builtins.str"],"extra_attrs":null,"type_ref":"builtins.list"}]],"readonly_keys":[],"required_keys":[]}}},"ModuleRegistryError":{".class":"SymbolTableNode","kind":"Gdef","node":{".class":"TypeInfo","_promote":[],"abstract_attributes":[],"alt_promote":null,"bases":["builtins.Exception"],"dataclass_transform_spec":null,"declared_metaclass":null,"defn":{".class":"ClassDef","fullname":"ai_core.module_registry.ModuleRegistryError","name":"ModuleRegistryError","type_vars":[]},"deletable_attributes":[],"deprecated":null,"flags":[],"fullname":"ai_core.module_registry.ModuleRegistryError","has_param_spec_type":false,"metaclass_type":null,"metadata":{},"module_name":"ai_core.module_registry","mro":["ai_core.module_registry.ModuleRegistryError","builtins.Exception","builtins.BaseException","builtins.object"],"names":{".class":"SymbolTable"},"self_type":{".class":"TypeVarType","default":{".class":"AnyType","missing_import_name":null,"source_any":null,"type_of_any":4},"fullname":"ai_core.module_registry.ModuleRegistryError.Self","id":0,"name":"Self","namespace":"","upper_bound":"ai_core.module_registry.ModuleRegistryError","values":[],"variance":0},"slots":null,"tuple_type":null,"type_vars":[],"typeddict_type":null}},"ModulesDict":{".class":"SymbolTableNode","kind":"Gdef","node":{".class":"TypeInfo","_promote":[],"abstract_attributes":[],"alt_promote":null,"bases":["typing._TypedDict"],"dataclass_transform_spec":null,"declared_metaclass":null,"defn":{".class":"ClassDef","fullname":"ai_core.module_registry.ModulesDict","name":"ModulesDict","type_vars":[]},"deletable_attributes":[],"deprecated":null,"flags":[],"fullname":"ai_core.module_registry.ModulesDict","has_param_spec_type":false,"metaclass_type":null,"metadata":{},"module_name":"ai_core.module_registry","mro":["ai_core.module_registry.ModulesDict","typing._TypedDict","typing.Mapping","typing.Collection","typing.Iterable","typing.Container","builtins.object"],"names":{".class":"SymbolTable"},"self_type":null,"slots":null,"tuple_type":null,"type_vars":[],"typeddict_type":{".class":"TypedDictType","fallback":"typing._TypedDict","items":[["modules",{".class":"Instance","args":["builtins.str",{".class":"TypeAliasType","args":[],"type_ref":"ai_core.module_registry.ModuleConfig"}],"extra_attrs":null,"type_ref":"builtins.dict"}]],"readonly_keys":[],"required_keys":[]}}},"Optional":{".class":"SymbolTableNode","cross_ref":"typing.Optional","kind":"Gdef","module_hidden":true,"module_public":false},"ResourceManager":{".class":"SymbolTableNode","cross_ref":"ai_core.resource_management.ResourceManager","kind":"Gdef","module_hidden":true,"module_public":false},"Set":{".class":"SymbolTableNode","cross_ref":"typing.Set","kind":"Gdef","module_hidden":true,"module_public":false},"Type":{".class":"SymbolTableNode","cross_ref":"typing.Type","kind":"Gdef","module_hidden":true,"module_public":false},"TypedDict":{".class":"SymbolTableNode","cross_ref":"typing.TypedDict","kind":"Gdef","module_hidden":true,"module_public":false},"Union":{".class":"SymbolTableNode","cross_ref":"typing.Union","kind":"Gdef","module_hidden":true,"module_public":false},"__annotations__":{".class":"SymbolTableNode","kind":"Gdef","node":{".class":"Var","flags":["is_ready"],"fullname":"ai_core.module_registry.__annotations__","name":"__annotations__","type":{".class":"Instance","args":["builtins.str",{".class":"AnyType","missing_import_name":null,"source_any":null,"type_of_any":6}],"extra_attrs":null,"type_ref":"builtins.dict"}}},"__doc__":{".class":"SymbolTableNode","kind":"Gdef","node":{".class":"Var","flags":["is_ready"],"fullname":"ai_core.module_registry.__doc__","name":"__doc__","type":"builtins.str"}},"__file__":{".class":"SymbolTableNode","kind":"Gdef","node":{".class":"Var","flags":["is_ready"],"fullname":"ai_core.module_registry.__file__","name":"__file__","type":"builtins.str"}},"__name__":{".class":"SymbolTableNode","kind":"Gdef","node":{".class":"Var","flags":["is_ready"],"fullname":"ai_core.module_registry.__name__","name":"__name__","type":"builtins.str"}},"__package__":{".class":"SymbolTableNode","kind":"Gdef","node":{".class":"Var","flags":["is_ready"],"fullname":"ai_core.module_registry.__package__","name":"__package__","type":"builtins.str"}},"__spec__":{".class":"SymbolTableNode","kind":"Gdef","node":{".class":"Var","flags":["is_ready"],"fullname":"ai_core.module_registry.__spec__","name":"__spec__","type":"_frozen_importlib.ModuleSpec"}},"asyncio":{".class":"SymbolTableNode","cross_ref":"asyncio","kind":"Gdef","module_hidden":true,"module_public":false},"inspect":{".class":"SymbolTableNode","cross_ref":"inspect","kind":"Gdef","module_hidden":true,"module_public":false},"json":{".class":"SymbolTableNode","cross_ref":"json","kind":"Gdef","module_hidden":true,"module_public":false},"logger":{".class":"SymbolTableNode","kind":"Gdef","node":{".class":"Var","flags":["is_inferred","has_explicit_value"],"fullname":"ai_core.module_registry.logger","name":"logger","type":"logging.Logger"}},"logging":{".class":"SymbolTableNode","cross_ref":"logging","kind":"Gdef","module_hidden":true,"module_public":false},"os":{".class":"SymbolTableNode","cross_ref":"os","kind":"Gdef","module_hidden":true,"module_public":false},"threading":{".class":"SymbolTableNode","cross_ref":"threading","kind":"Gdef","module_hidden":true,"module_public":false},"time":{".class":"SymbolTableNode","cross_ref":"time","kind":"Gdef","module_hidden":true,"module_public":false}},"path":"D:\\Libraries\\Documents\\GitHub\\vAIn_p2p_AGI\\ai_core\\module_registry.py"}