{".class":"MypyFile","_fullname":"eth_utils.abi","future_import_flags":[],"is_partial_stub_package":false,"is_stub":false,"names":{".class":"SymbolTable","ABI":{".class":"SymbolTableNode","cross_ref":"eth_typing.abi.ABI","kind":"Gdef","module_hidden":true,"module_public":false},"ABIComponent":{".class":"SymbolTableNode","cross_ref":"eth_typing.abi.ABIComponent","kind":"Gdef","module_hidden":true,"module_public":false},"ABIConstructor":{".class":"SymbolTableNode","cross_ref":"eth_typing.abi.ABIConstructor","kind":"Gdef","module_hidden":true,"module_public":false},"ABIElement":{".class":"SymbolTableNode","cross_ref":"eth_typing.abi.ABIElement","kind":"Gdef","module_hidden":true,"module_public":false},"ABIError":{".class":"SymbolTableNode","cross_ref":"eth_typing.abi.ABIError","kind":"Gdef","module_hidden":true,"module_public":false},"ABIEvent":{".class":"SymbolTableNode","cross_ref":"eth_typing.abi.ABIEvent","kind":"Gdef","module_hidden":true,"module_public":false},"ABIFallback":{".class":"SymbolTableNode","cross_ref":"eth_typing.abi.ABIFallback","kind":"Gdef","module_hidden":true,"module_public":false},"ABIFunction":{".class":"SymbolTableNode","cross_ref":"eth_typing.abi.ABIFunction","kind":"Gdef","module_hidden":true,"module_public":false},"ABIReceive":{".class":"SymbolTableNode","cross_ref":"eth_typing.abi.ABIReceive","kind":"Gdef","module_hidden":true,"module_public":false},"Any":{".class":"SymbolTableNode","cross_ref":"typing.Any","kind":"Gdef","module_hidden":true,"module_public":false},"Dict":{".class":"SymbolTableNode","cross_ref":"typing.Dict","kind":"Gdef","module_hidden":true,"module_public":false},"Iterable":{".class":"SymbolTableNode","cross_ref":"typing.Iterable","kind":"Gdef","module_hidden":true,"module_public":false},"List":{".class":"SymbolTableNode","cross_ref":"typing.List","kind":"Gdef","module_hidden":true,"module_public":false},"Literal":{".class":"SymbolTableNode","cross_ref":"typing.Literal","kind":"Gdef","module_hidden":true,"module_public":false},"Mapping":{".class":"SymbolTableNode","cross_ref":"typing.Mapping","kind":"Gdef","module_hidden":true,"module_public":false},"Optional":{".class":"SymbolTableNode","cross_ref":"typing.Optional","kind":"Gdef","module_hidden":true,"module_public":false},"Sequence":{".class":"SymbolTableNode","cross_ref":"typing.Sequence","kind":"Gdef","module_hidden":true,"module_public":false},"Tuple":{".class":"SymbolTableNode","cross_ref":"typing.Tuple","kind":"Gdef","module_hidden":true,"module_public":false},"Union":{".class":"SymbolTableNode","cross_ref":"typing.Union","kind":"Gdef","module_hidden":true,"module_public":false},"__annotations__":{".class":"SymbolTableNode","kind":"Gdef","node":{".class":"Var","flags":["is_ready"],"fullname":"eth_utils.abi.__annotations__","name":"__annotations__","type":{".class":"Instance","args":["builtins.str",{".class":"AnyType","missing_import_name":null,"source_any":null,"type_of_any":6}],"extra_attrs":null,"type_ref":"builtins.dict"}}},"__doc__":{".class":"SymbolTableNode","kind":"Gdef","node":{".class":"Var","flags":["is_ready"],"fullname":"eth_utils.abi.__doc__","name":"__doc__","type":"builtins.str"}},"__file__":{".class":"SymbolTableNode","kind":"Gdef","node":{".class":"Var","flags":["is_ready"],"fullname":"eth_utils.abi.__file__","name":"__file__","type":"builtins.str"}},"__name__":{".class":"SymbolTableNode","kind":"Gdef","node":{".class":"Var","flags":["is_ready"],"fullname":"eth_utils.abi.__name__","name":"__name__","type":"builtins.str"}},"__package__":{".class":"SymbolTableNode","kind":"Gdef","node":{".class":"Var","flags":["is_ready"],"fullname":"eth_utils.abi.__package__","name":"__package__","type":"builtins.str"}},"__spec__":{".class":"SymbolTableNode","kind":"Gdef","node":{".class":"Var","flags":["is_ready"],"fullname":"eth_utils.abi.__spec__","name":"__spec__","type":"_frozen_importlib.ModuleSpec"}},"_align_abi_input":{".class":"SymbolTableNode","kind":"Gdef","node":{".class":"FuncDef","abstract_status":0,"arg_kinds":[0,0],"arg_names":["arg_abi","normalized_arg"],"dataclass_transform_spec":null,"deprecated":null,"flags":[],"fullname":"eth_utils.abi._align_abi_input","name":"_align_abi_input","type":{".class":"CallableType","arg_kinds":[0,0],"arg_names":["arg_abi","normalized_arg"],"arg_types":[{".class":"TypeAliasType","args":[],"type_ref":"eth_typing.abi.ABIComponent"},{".class":"AnyType","missing_import_name":null,"source_any":null,"type_of_any":2}],"bound_args":[],"def_extras":{"first_arg":null},"fallback":"builtins.function","from_concatenate":false,"implicit":false,"imprecise_arg_kinds":false,"is_ellipsis_args":false,"name":"_align_abi_input","ret_type":{".class":"UnionType","items":[{".class":"AnyType","missing_import_name":null,"source_any":null,"type_of_any":2},{".class":"Instance","args":[{".class":"AnyType","missing_import_name":null,"source_any":null,"type_of_any":2}],"extra_attrs":null,"type_ref":"builtins.tuple"}],"uses_pep604_syntax":false},"type_guard":null,"type_is":null,"unpack_kwargs":false,"variables":[]}}},"_get_tuple_type_str_and_dims":{".class":"SymbolTableNode","kind":"Gdef","node":{".class":"FuncDef","abstract_status":0,"arg_kinds":[0],"arg_names":["s"],"dataclass_transform_spec":null,"deprecated":null,"flags":[],"fullname":"eth_utils.abi._get_tuple_type_str_and_dims","name":"_get_tuple_type_str_and_dims","type":{".class":"CallableType","arg_kinds":[0],"arg_names":["s"],"arg_types":["builtins.str"],"bound_args":[],"def_extras":{"first_arg":null},"fallback":"builtins.function","from_concatenate":false,"implicit":false,"imprecise_arg_kinds":false,"is_ellipsis_args":false,"name":"_get_tuple_type_str_and_dims","ret_type":{".class":"UnionType","items":[{".class":"TupleType","implicit":false,"items":["builtins.str",{".class":"UnionType","items":["builtins.str",{".class":"NoneType"}],"uses_pep604_syntax":false}],"partial_fallback":{".class":"Instance","args":[{".class":"AnyType","missing_import_name":null,"source_any":null,"type_of_any":6}],"extra_attrs":null,"type_ref":"builtins.tuple"}},{".class":"NoneType"}],"uses_pep604_syntax":false},"type_guard":null,"type_is":null,"unpack_kwargs":false,"variables":[]}}},"_raise_if_fallback_or_receive_abi":{".class":"SymbolTableNode","kind":"Gdef","node":{".class":"FuncDef","abstract_status":0,"arg_kinds":[0],"arg_names":["abi_element"],"dataclass_transform_spec":null,"deprecated":null,"flags":[],"fullname":"eth_utils.abi._raise_if_fallback_or_receive_abi","name":"_raise_if_fallback_or_receive_abi","type":{".class":"CallableType","arg_kinds":[0],"arg_names":["abi_element"],"arg_types":[{".class":"TypeAliasType","args":[],"type_ref":"eth_typing.abi.ABIElement"}],"bound_args":[],"def_extras":{"first_arg":null},"fallback":"builtins.function","from_concatenate":false,"implicit":false,"imprecise_arg_kinds":false,"is_ellipsis_args":false,"name":"_raise_if_fallback_or_receive_abi","ret_type":{".class":"NoneType"},"type_guard":null,"type_is":null,"unpack_kwargs":false,"variables":[]}}},"_raise_if_not_function_abi":{".class":"SymbolTableNode","kind":"Gdef","node":{".class":"FuncDef","abstract_status":0,"arg_kinds":[0],"arg_names":["abi_element"],"dataclass_transform_spec":null,"deprecated":null,"flags":[],"fullname":"eth_utils.abi._raise_if_not_function_abi","name":"_raise_if_not_function_abi","type":{".class":"CallableType","arg_kinds":[0],"arg_names":["abi_element"],"arg_types":[{".class":"TypeAliasType","args":[],"type_ref":"eth_typing.abi.ABIElement"}],"bound_args":[],"def_extras":{"first_arg":null},"fallback":"builtins.function","from_concatenate":false,"implicit":false,"imprecise_arg_kinds":false,"is_ellipsis_args":false,"name":"_raise_if_not_function_abi","ret_type":{".class":"NoneType"},"type_guard":null,"type_is":null,"unpack_kwargs":false,"variables":[]}}},"abc":{".class":"SymbolTableNode","cross_ref":"collections.abc","kind":"Gdef","module_hidden":true,"module_public":false},"abi_to_signature":{".class":"SymbolTableNode","kind":"Gdef","node":{".class":"FuncDef","abstract_status":0,"arg_kinds":[0],"arg_names":["abi_element"],"dataclass_transform_spec":null,"deprecated":null,"flags":[],"fullname":"eth_utils.abi.abi_to_signature","name":"abi_to_signature","type":{".class":"CallableType","arg_kinds":[0],"arg_names":["abi_element"],"arg_types":[{".class":"TypeAliasType","args":[],"type_ref":"eth_typing.abi.ABIElement"}],"bound_args":[],"def_extras":{"first_arg":null},"fallback":"builtins.function","from_concatenate":false,"implicit":false,"imprecise_arg_kinds":false,"is_ellipsis_args":false,"name":"abi_to_signature","ret_type":"builtins.str","type_guard":null,"type_is":null,"unpack_kwargs":false,"variables":[]}}},"cast":{".class":"SymbolTableNode","cross_ref":"typing.cast","kind":"Gdef","module_hidden":true,"module_public":false},"collapse_if_tuple":{".class":"SymbolTableNode","kind":"Gdef","node":{".class":"FuncDef","abstract_status":0,"arg_kinds":[0],"arg_names":["abi"],"dataclass_transform_spec":null,"deprecated":null,"flags":[],"fullname":"eth_utils.abi.collapse_if_tuple","name":"collapse_if_tuple","type":{".class":"CallableType","arg_kinds":[0],"arg_names":["abi"],"arg_types":[{".class":"UnionType","items":[{".class":"TypeAliasType","args":[],"type_ref":"eth_typing.abi.ABIComponent"},{".class":"Instance","args":["builtins.str",{".class":"AnyType","missing_import_name":null,"source_any":null,"type_of_any":2}],"extra_attrs":null,"type_ref":"builtins.dict"},"builtins.str"],"uses_pep604_syntax":false}],"bound_args":[],"def_extras":{"first_arg":null},"fallback":"builtins.function","from_concatenate":false,"implicit":false,"imprecise_arg_kinds":false,"is_ellipsis_args":false,"name":"collapse_if_tuple","ret_type":"builtins.str","type_guard":null,"type_is":null,"unpack_kwargs":false,"variables":[]}}},"copy":{".class":"SymbolTableNode","cross_ref":"copy","kind":"Gdef","module_hidden":true,"module_public":false},"event_abi_to_log_topic":{".class":"SymbolTableNode","kind":"Gdef","node":{".class":"FuncDef","abstract_status":0,"arg_kinds":[0],"arg_names":["event_abi"],"dataclass_transform_spec":null,"deprecated":null,"flags":[],"fullname":"eth_utils.abi.event_abi_to_log_topic","name":"event_abi_to_log_topic","type":{".class":"CallableType","arg_kinds":[0],"arg_names":["event_abi"],"arg_types":[{".class":"TypeAliasType","args":[],"type_ref":"eth_typing.abi.ABIEvent"}],"bound_args":[],"def_extras":{"first_arg":null},"fallback":"builtins.function","from_concatenate":false,"implicit":false,"imprecise_arg_kinds":false,"is_ellipsis_args":false,"name":"event_abi_to_log_topic","ret_type":"builtins.bytes","type_guard":null,"type_is":null,"unpack_kwargs":false,"variables":[]}}},"event_signature_to_log_topic":{".class":"SymbolTableNode","kind":"Gdef","node":{".class":"FuncDef","abstract_status":0,"arg_kinds":[0],"arg_names":["event_signature"],"dataclass_transform_spec":null,"deprecated":null,"flags":[],"fullname":"eth_utils.abi.event_signature_to_log_topic","name":"event_signature_to_log_topic","type":{".class":"CallableType","arg_kinds":[0],"arg_names":["event_signature"],"arg_types":["builtins.str"],"bound_args":[],"def_extras":{"first_arg":null},"fallback":"builtins.function","from_concatenate":false,"implicit":false,"imprecise_arg_kinds":false,"is_ellipsis_args":false,"name":"event_signature_to_log_topic","ret_type":"builtins.bytes","type_guard":null,"type_is":null,"unpack_kwargs":false,"variables":[]}}},"filter_abi_by_name":{".class":"SymbolTableNode","kind":"Gdef","node":{".class":"FuncDef","abstract_status":0,"arg_kinds":[0,0],"arg_names":["abi_name","contract_abi"],"dataclass_transform_spec":null,"deprecated":null,"flags":[],"fullname":"eth_utils.abi.filter_abi_by_name","name":"filter_abi_by_name","type":{".class":"CallableType","arg_kinds":[0,0],"arg_names":["abi_name","contract_abi"],"arg_types":["builtins.str",{".class":"TypeAliasType","args":[],"type_ref":"eth_typing.abi.ABI"}],"bound_args":[],"def_extras":{"first_arg":null},"fallback":"builtins.function","from_concatenate":false,"implicit":false,"imprecise_arg_kinds":false,"is_ellipsis_args":false,"name":"filter_abi_by_name","ret_type":{".class":"Instance","args":[{".class":"TypeAliasType","args":[],"type_ref":"eth_typing.abi.ABIElement"}],"extra_attrs":null,"type_ref":"typing.Sequence"},"type_guard":null,"type_is":null,"unpack_kwargs":false,"variables":[]}}},"filter_abi_by_type":{".class":"SymbolTableNode","kind":"Gdef","node":{".class":"OverloadedFuncDef","deprecated":null,"flags":[],"fullname":"eth_utils.abi.filter_abi_by_type","impl":{".class":"FuncDef","abstract_status":0,"arg_kinds":[0,0],"arg_names":["abi_type","contract_abi"],"dataclass_transform_spec":null,"deprecated":null,"flags":["is_overload"],"fullname":"eth_utils.abi.filter_abi_by_type","name":"filter_abi_by_type","type":{".class":"CallableType","arg_kinds":[0,0],"arg_names":["abi_type","contract_abi"],"arg_types":[{".class":"UnionType","items":[{".class":"LiteralType","fallback":"builtins.str","value":"function"},{".class":"LiteralType","fallback":"builtins.str","value":"constructor"},{".class":"LiteralType","fallback":"builtins.str","value":"fallback"},{".class":"LiteralType","fallback":"builtins.str","value":"receive"},{".class":"LiteralType","fallback":"builtins.str","value":"event"},{".class":"LiteralType","fallback":"builtins.str","value":"error"}],"uses_pep604_syntax":false},{".class":"TypeAliasType","args":[],"type_ref":"eth_typing.abi.ABI"}],"bound_args":[],"def_extras":{"first_arg":null},"fallback":"builtins.function","from_concatenate":false,"implicit":false,"imprecise_arg_kinds":false,"is_ellipsis_args":false,"name":"filter_abi_by_type","ret_type":{".class":"Instance","args":[{".class":"UnionType","items":[{".class":"TypeAliasType","args":[],"type_ref":"eth_typing.abi.ABIFunction"},{".class":"TypeAliasType","args":[],"type_ref":"eth_typing.abi.ABIConstructor"},{".class":"TypeAliasType","args":[],"type_ref":"eth_typing.abi.ABIFallback"},{".class":"TypeAliasType","args":[],"type_ref":"eth_typing.abi.ABIReceive"},{".class":"TypeAliasType","args":[],"type_ref":"eth_typing.abi.ABIEvent"},{".class":"TypeAliasType","args":[],"type_ref":"eth_typing.abi.ABIError"}],"uses_pep604_syntax":false}],"extra_attrs":null,"type_ref":"typing.Sequence"},"type_guard":null,"type_is":null,"unpack_kwargs":false,"variables":[]}},"items":[{".class":"Decorator","func":{".class":"FuncDef","abstract_status":0,"arg_kinds":[0,0],"arg_names":["abi_type","contract_abi"],"dataclass_transform_spec":null,"deprecated":null,"flags":["is_overload","is_decorated"],"fullname":"eth_utils.abi.filter_abi_by_type","name":"filter_abi_by_type","type":{".class":"CallableType","arg_kinds":[0,0],"arg_names":["abi_type","contract_abi"],"arg_types":[{".class":"LiteralType","fallback":"builtins.str","value":"function"},{".class":"TypeAliasType","args":[],"type_ref":"eth_typing.abi.ABI"}],"bound_args":[],"def_extras":{"first_arg":null},"fallback":"builtins.function","from_concatenate":false,"implicit":false,"imprecise_arg_kinds":false,"is_ellipsis_args":false,"name":"filter_abi_by_type","ret_type":{".class":"Instance","args":[{".class":"TypeAliasType","args":[],"type_ref":"eth_typing.abi.ABIFunction"}],"extra_attrs":null,"type_ref":"typing.Sequence"},"type_guard":null,"type_is":null,"unpack_kwargs":false,"variables":[]}},"is_overload":true,"var":{".class":"Var","flags":["is_ready","is_inferred"],"fullname":"eth_utils.abi.filter_abi_by_type","name":"filter_abi_by_type","type":{".class":"CallableType","arg_kinds":[0,0],"arg_names":["abi_type","contract_abi"],"arg_types":[{".class":"LiteralType","fallback":"builtins.str","value":"function"},{".class":"TypeAliasType","args":[],"type_ref":"eth_typing.abi.ABI"}],"bound_args":[],"def_extras":{"first_arg":null},"fallback":"builtins.function","from_concatenate":false,"implicit":false,"imprecise_arg_kinds":false,"is_ellipsis_args":false,"name":"filter_abi_by_type","ret_type":{".class":"Instance","args":[{".class":"TypeAliasType","args":[],"type_ref":"eth_typing.abi.ABIFunction"}],"extra_attrs":null,"type_ref":"typing.Sequence"},"type_guard":null,"type_is":null,"unpack_kwargs":false,"variables":[]}}},{".class":"Decorator","func":{".class":"FuncDef","abstract_status":0,"arg_kinds":[0,0],"arg_names":["abi_type","contract_abi"],"dataclass_transform_spec":null,"deprecated":null,"flags":["is_overload","is_decorated"],"fullname":"eth_utils.abi.filter_abi_by_type","name":"filter_abi_by_type","type":{".class":"CallableType","arg_kinds":[0,0],"arg_names":["abi_type","contract_abi"],"arg_types":[{".class":"LiteralType","fallback":"builtins.str","value":"constructor"},{".class":"TypeAliasType","args":[],"type_ref":"eth_typing.abi.ABI"}],"bound_args":[],"def_extras":{"first_arg":null},"fallback":"builtins.function","from_concatenate":false,"implicit":false,"imprecise_arg_kinds":false,"is_ellipsis_args":false,"name":"filter_abi_by_type","ret_type":{".class":"Instance","args":[{".class":"TypeAliasType","args":[],"type_ref":"eth_typing.abi.ABIConstructor"}],"extra_attrs":null,"type_ref":"typing.Sequence"},"type_guard":null,"type_is":null,"unpack_kwargs":false,"variables":[]}},"is_overload":true,"var":{".class":"Var","flags":["is_ready","is_inferred"],"fullname":"eth_utils.abi.filter_abi_by_type","name":"filter_abi_by_type","type":{".class":"CallableType","arg_kinds":[0,0],"arg_names":["abi_type","contract_abi"],"arg_types":[{".class":"LiteralType","fallback":"builtins.str","value":"constructor"},{".class":"TypeAliasType","args":[],"type_ref":"eth_typing.abi.ABI"}],"bound_args":[],"def_extras":{"first_arg":null},"fallback":"builtins.function","from_concatenate":false,"implicit":false,"imprecise_arg_kinds":false,"is_ellipsis_args":false,"name":"filter_abi_by_type","ret_type":{".class":"Instance","args":[{".class":"TypeAliasType","args":[],"type_ref":"eth_typing.abi.ABIConstructor"}],"extra_attrs":null,"type_ref":"typing.Sequence"},"type_guard":null,"type_is":null,"unpack_kwargs":false,"variables":[]}}},{".class":"Decorator","func":{".class":"FuncDef","abstract_status":0,"arg_kinds":[0,0],"arg_names":["abi_type","contract_abi"],"dataclass_transform_spec":null,"deprecated":null,"flags":["is_overload","is_decorated"],"fullname":"eth_utils.abi.filter_abi_by_type","name":"filter_abi_by_type","type":{".class":"CallableType","arg_kinds":[0,0],"arg_names":["abi_type","contract_abi"],"arg_types":[{".class":"LiteralType","fallback":"builtins.str","value":"fallback"},{".class":"TypeAliasType","args":[],"type_ref":"eth_typing.abi.ABI"}],"bound_args":[],"def_extras":{"first_arg":null},"fallback":"builtins.function","from_concatenate":false,"implicit":false,"imprecise_arg_kinds":false,"is_ellipsis_args":false,"name":"filter_abi_by_type","ret_type":{".class":"Instance","args":[{".class":"TypeAliasType","args":[],"type_ref":"eth_typing.abi.ABIFallback"}],"extra_attrs":null,"type_ref":"typing.Sequence"},"type_guard":null,"type_is":null,"unpack_kwargs":false,"variables":[]}},"is_overload":true,"var":{".class":"Var","flags":["is_ready","is_inferred"],"fullname":"eth_utils.abi.filter_abi_by_type","name":"filter_abi_by_type","type":{".class":"CallableType","arg_kinds":[0,0],"arg_names":["abi_type","contract_abi"],"arg_types":[{".class":"LiteralType","fallback":"builtins.str","value":"fallback"},{".class":"TypeAliasType","args":[],"type_ref":"eth_typing.abi.ABI"}],"bound_args":[],"def_extras":{"first_arg":null},"fallback":"builtins.function","from_concatenate":false,"implicit":false,"imprecise_arg_kinds":false,"is_ellipsis_args":false,"name":"filter_abi_by_type","ret_type":{".class":"Instance","args":[{".class":"TypeAliasType","args":[],"type_ref":"eth_typing.abi.ABIFallback"}],"extra_attrs":null,"type_ref":"typing.Sequence"},"type_guard":null,"type_is":null,"unpack_kwargs":false,"variables":[]}}},{".class":"Decorator","func":{".class":"FuncDef","abstract_status":0,"arg_kinds":[0,0],"arg_names":["abi_type","contract_abi"],"dataclass_transform_spec":null,"deprecated":null,"flags":["is_overload","is_decorated"],"fullname":"eth_utils.abi.filter_abi_by_type","name":"filter_abi_by_type","type":{".class":"CallableType","arg_kinds":[0,0],"arg_names":["abi_type","contract_abi"],"arg_types":[{".class":"LiteralType","fallback":"builtins.str","value":"receive"},{".class":"TypeAliasType","args":[],"type_ref":"eth_typing.abi.ABI"}],"bound_args":[],"def_extras":{"first_arg":null},"fallback":"builtins.function","from_concatenate":false,"implicit":false,"imprecise_arg_kinds":false,"is_ellipsis_args":false,"name":"filter_abi_by_type","ret_type":{".class":"Instance","args":[{".class":"TypeAliasType","args":[],"type_ref":"eth_typing.abi.ABIReceive"}],"extra_attrs":null,"type_ref":"typing.Sequence"},"type_guard":null,"type_is":null,"unpack_kwargs":false,"variables":[]}},"is_overload":true,"var":{".class":"Var","flags":["is_ready","is_inferred"],"fullname":"eth_utils.abi.filter_abi_by_type","name":"filter_abi_by_type","type":{".class":"CallableType","arg_kinds":[0,0],"arg_names":["abi_type","contract_abi"],"arg_types":[{".class":"LiteralType","fallback":"builtins.str","value":"receive"},{".class":"TypeAliasType","args":[],"type_ref":"eth_typing.abi.ABI"}],"bound_args":[],"def_extras":{"first_arg":null},"fallback":"builtins.function","from_concatenate":false,"implicit":false,"imprecise_arg_kinds":false,"is_ellipsis_args":false,"name":"filter_abi_by_type","ret_type":{".class":"Instance","args":[{".class":"TypeAliasType","args":[],"type_ref":"eth_typing.abi.ABIReceive"}],"extra_attrs":null,"type_ref":"typing.Sequence"},"type_guard":null,"type_is":null,"unpack_kwargs":false,"variables":[]}}},{".class":"Decorator","func":{".class":"FuncDef","abstract_status":0,"arg_kinds":[0,0],"arg_names":["abi_type","contract_abi"],"dataclass_transform_spec":null,"deprecated":null,"flags":["is_overload","is_decorated"],"fullname":"eth_utils.abi.filter_abi_by_type","name":"filter_abi_by_type","type":{".class":"CallableType","arg_kinds":[0,0],"arg_names":["abi_type","contract_abi"],"arg_types":[{".class":"LiteralType","fallback":"builtins.str","value":"event"},{".class":"TypeAliasType","args":[],"type_ref":"eth_typing.abi.ABI"}],"bound_args":[],"def_extras":{"first_arg":null},"fallback":"builtins.function","from_concatenate":false,"implicit":false,"imprecise_arg_kinds":false,"is_ellipsis_args":false,"name":"filter_abi_by_type","ret_type":{".class":"Instance","args":[{".class":"TypeAliasType","args":[],"type_ref":"eth_typing.abi.ABIEvent"}],"extra_attrs":null,"type_ref":"typing.Sequence"},"type_guard":null,"type_is":null,"unpack_kwargs":false,"variables":[]}},"is_overload":true,"var":{".class":"Var","flags":["is_ready","is_inferred"],"fullname":"eth_utils.abi.filter_abi_by_type","name":"filter_abi_by_type","type":{".class":"CallableType","arg_kinds":[0,0],"arg_names":["abi_type","contract_abi"],"arg_types":[{".class":"LiteralType","fallback":"builtins.str","value":"event"},{".class":"TypeAliasType","args":[],"type_ref":"eth_typing.abi.ABI"}],"bound_args":[],"def_extras":{"first_arg":null},"fallback":"builtins.function","from_concatenate":false,"implicit":false,"imprecise_arg_kinds":false,"is_ellipsis_args":false,"name":"filter_abi_by_type","ret_type":{".class":"Instance","args":[{".class":"TypeAliasType","args":[],"type_ref":"eth_typing.abi.ABIEvent"}],"extra_attrs":null,"type_ref":"typing.Sequence"},"type_guard":null,"type_is":null,"unpack_kwargs":false,"variables":[]}}},{".class":"Decorator","func":{".class":"FuncDef","abstract_status":0,"arg_kinds":[0,0],"arg_names":["abi_type","contract_abi"],"dataclass_transform_spec":null,"deprecated":null,"flags":["is_overload","is_decorated"],"fullname":"eth_utils.abi.filter_abi_by_type","name":"filter_abi_by_type","type":{".class":"CallableType","arg_kinds":[0,0],"arg_names":["abi_type","contract_abi"],"arg_types":[{".class":"LiteralType","fallback":"builtins.str","value":"error"},{".class":"TypeAliasType","args":[],"type_ref":"eth_typing.abi.ABI"}],"bound_args":[],"def_extras":{"first_arg":null},"fallback":"builtins.function","from_concatenate":false,"implicit":false,"imprecise_arg_kinds":false,"is_ellipsis_args":false,"name":"filter_abi_by_type","ret_type":{".class":"Instance","args":[{".class":"TypeAliasType","args":[],"type_ref":"eth_typing.abi.ABIError"}],"extra_attrs":null,"type_ref":"typing.Sequence"},"type_guard":null,"type_is":null,"unpack_kwargs":false,"variables":[]}},"is_overload":true,"var":{".class":"Var","flags":["is_ready","is_inferred"],"fullname":"eth_utils.abi.filter_abi_by_type","name":"filter_abi_by_type","type":{".class":"CallableType","arg_kinds":[0,0],"arg_names":["abi_type","contract_abi"],"arg_types":[{".class":"LiteralType","fallback":"builtins.str","value":"error"},{".class":"TypeAliasType","args":[],"type_ref":"eth_typing.abi.ABI"}],"bound_args":[],"def_extras":{"first_arg":null},"fallback":"builtins.function","from_concatenate":false,"implicit":false,"imprecise_arg_kinds":false,"is_ellipsis_args":false,"name":"filter_abi_by_type","ret_type":{".class":"Instance","args":[{".class":"TypeAliasType","args":[],"type_ref":"eth_typing.abi.ABIError"}],"extra_attrs":null,"type_ref":"typing.Sequence"},"type_guard":null,"type_is":null,"unpack_kwargs":false,"variables":[]}}}],"type":{".class":"Overloaded","items":[{".class":"CallableType","arg_kinds":[0,0],"arg_names":["abi_type","contract_abi"],"arg_types":[{".class":"LiteralType","fallback":"builtins.str","value":"function"},{".class":"TypeAliasType","args":[],"type_ref":"eth_typing.abi.ABI"}],"bound_args":[],"def_extras":{"first_arg":null},"fallback":"builtins.function","from_concatenate":false,"implicit":false,"imprecise_arg_kinds":false,"is_ellipsis_args":false,"name":"filter_abi_by_type","ret_type":{".class":"Instance","args":[{".class":"TypeAliasType","args":[],"type_ref":"eth_typing.abi.ABIFunction"}],"extra_attrs":null,"type_ref":"typing.Sequence"},"type_guard":null,"type_is":null,"unpack_kwargs":false,"variables":[]},{".class":"CallableType","arg_kinds":[0,0],"arg_names":["abi_type","contract_abi"],"arg_types":[{".class":"LiteralType","fallback":"builtins.str","value":"constructor"},{".class":"TypeAliasType","args":[],"type_ref":"eth_typing.abi.ABI"}],"bound_args":[],"def_extras":{"first_arg":null},"fallback":"builtins.function","from_concatenate":false,"implicit":false,"imprecise_arg_kinds":false,"is_ellipsis_args":false,"name":"filter_abi_by_type","ret_type":{".class":"Instance","args":[{".class":"TypeAliasType","args":[],"type_ref":"eth_typing.abi.ABIConstructor"}],"extra_attrs":null,"type_ref":"typing.Sequence"},"type_guard":null,"type_is":null,"unpack_kwargs":false,"variables":[]},{".class":"CallableType","arg_kinds":[0,0],"arg_names":["abi_type","contract_abi"],"arg_types":[{".class":"LiteralType","fallback":"builtins.str","value":"fallback"},{".class":"TypeAliasType","args":[],"type_ref":"eth_typing.abi.ABI"}],"bound_args":[],"def_extras":{"first_arg":null},"fallback":"builtins.function","from_concatenate":false,"implicit":false,"imprecise_arg_kinds":false,"is_ellipsis_args":false,"name":"filter_abi_by_type","ret_type":{".class":"Instance","args":[{".class":"TypeAliasType","args":[],"type_ref":"eth_typing.abi.ABIFallback"}],"extra_attrs":null,"type_ref":"typing.Sequence"},"type_guard":null,"type_is":null,"unpack_kwargs":false,"variables":[]},{".class":"CallableType","arg_kinds":[0,0],"arg_names":["abi_type","contract_abi"],"arg_types":[{".class":"LiteralType","fallback":"builtins.str","value":"receive"},{".class":"TypeAliasType","args":[],"type_ref":"eth_typing.abi.ABI"}],"bound_args":[],"def_extras":{"first_arg":null},"fallback":"builtins.function","from_concatenate":false,"implicit":false,"imprecise_arg_kinds":false,"is_ellipsis_args":false,"name":"filter_abi_by_type","ret_type":{".class":"Instance","args":[{".class":"TypeAliasType","args":[],"type_ref":"eth_typing.abi.ABIReceive"}],"extra_attrs":null,"type_ref":"typing.Sequence"},"type_guard":null,"type_is":null,"unpack_kwargs":false,"variables":[]},{".class":"CallableType","arg_kinds":[0,0],"arg_names":["abi_type","contract_abi"],"arg_types":[{".class":"LiteralType","fallback":"builtins.str","value":"event"},{".class":"TypeAliasType","args":[],"type_ref":"eth_typing.abi.ABI"}],"bound_args":[],"def_extras":{"first_arg":null},"fallback":"builtins.function","from_concatenate":false,"implicit":false,"imprecise_arg_kinds":false,"is_ellipsis_args":false,"name":"filter_abi_by_type","ret_type":{".class":"Instance","args":[{".class":"TypeAliasType","args":[],"type_ref":"eth_typing.abi.ABIEvent"}],"extra_attrs":null,"type_ref":"typing.Sequence"},"type_guard":null,"type_is":null,"unpack_kwargs":false,"variables":[]},{".class":"CallableType","arg_kinds":[0,0],"arg_names":["abi_type","contract_abi"],"arg_types":[{".class":"LiteralType","fallback":"builtins.str","value":"error"},{".class":"TypeAliasType","args":[],"type_ref":"eth_typing.abi.ABI"}],"bound_args":[],"def_extras":{"first_arg":null},"fallback":"builtins.function","from_concatenate":false,"implicit":false,"imprecise_arg_kinds":false,"is_ellipsis_args":false,"name":"filter_abi_by_type","ret_type":{".class":"Instance","args":[{".class":"TypeAliasType","args":[],"type_ref":"eth_typing.abi.ABIError"}],"extra_attrs":null,"type_ref":"typing.Sequence"},"type_guard":null,"type_is":null,"unpack_kwargs":false,"variables":[]}]}}},"function_abi_to_4byte_selector":{".class":"SymbolTableNode","kind":"Gdef","node":{".class":"FuncDef","abstract_status":0,"arg_kinds":[0],"arg_names":["abi_element"],"dataclass_transform_spec":null,"deprecated":null,"flags":[],"fullname":"eth_utils.abi.function_abi_to_4byte_selector","name":"function_abi_to_4byte_selector","type":{".class":"CallableType","arg_kinds":[0],"arg_names":["abi_element"],"arg_types":[{".class":"TypeAliasType","args":[],"type_ref":"eth_typing.abi.ABIElement"}],"bound_args":[],"def_extras":{"first_arg":null},"fallback":"builtins.function","from_concatenate":false,"implicit":false,"imprecise_arg_kinds":false,"is_ellipsis_args":false,"name":"function_abi_to_4byte_selector","ret_type":"builtins.bytes","type_guard":null,"type_is":null,"unpack_kwargs":false,"variables":[]}}},"function_signature_to_4byte_selector":{".class":"SymbolTableNode","kind":"Gdef","node":{".class":"FuncDef","abstract_status":0,"arg_kinds":[0],"arg_names":["function_signature"],"dataclass_transform_spec":null,"deprecated":null,"flags":[],"fullname":"eth_utils.abi.function_signature_to_4byte_selector","name":"function_signature_to_4byte_selector","type":{".class":"CallableType","arg_kinds":[0],"arg_names":["function_signature"],"arg_types":["builtins.str"],"bound_args":[],"def_extras":{"first_arg":null},"fallback":"builtins.function","from_concatenate":false,"implicit":false,"imprecise_arg_kinds":false,"is_ellipsis_args":false,"name":"function_signature_to_4byte_selector","ret_type":"builtins.bytes","type_guard":null,"type_is":null,"unpack_kwargs":false,"variables":[]}}},"get_abi_input_names":{".class":"SymbolTableNode","kind":"Gdef","node":{".class":"FuncDef","abstract_status":0,"arg_kinds":[0],"arg_names":["abi_element"],"dataclass_transform_spec":null,"deprecated":null,"flags":[],"fullname":"eth_utils.abi.get_abi_input_names","name":"get_abi_input_names","type":{".class":"CallableType","arg_kinds":[0],"arg_names":["abi_element"],"arg_types":[{".class":"TypeAliasType","args":[],"type_ref":"eth_typing.abi.ABIElement"}],"bound_args":[],"def_extras":{"first_arg":null},"fallback":"builtins.function","from_concatenate":false,"implicit":false,"imprecise_arg_kinds":false,"is_ellipsis_args":false,"name":"get_abi_input_names","ret_type":{".class":"Instance","args":["builtins.str"],"extra_attrs":null,"type_ref":"builtins.list"},"type_guard":null,"type_is":null,"unpack_kwargs":false,"variables":[]}}},"get_abi_input_types":{".class":"SymbolTableNode","kind":"Gdef","node":{".class":"FuncDef","abstract_status":0,"arg_kinds":[0],"arg_names":["abi_element"],"dataclass_transform_spec":null,"deprecated":null,"flags":[],"fullname":"eth_utils.abi.get_abi_input_types","name":"get_abi_input_types","type":{".class":"CallableType","arg_kinds":[0],"arg_names":["abi_element"],"arg_types":[{".class":"TypeAliasType","args":[],"type_ref":"eth_typing.abi.ABIElement"}],"bound_args":[],"def_extras":{"first_arg":null},"fallback":"builtins.function","from_concatenate":false,"implicit":false,"imprecise_arg_kinds":false,"is_ellipsis_args":false,"name":"get_abi_input_types","ret_type":{".class":"Instance","args":["builtins.str"],"extra_attrs":null,"type_ref":"builtins.list"},"type_guard":null,"type_is":null,"unpack_kwargs":false,"variables":[]}}},"get_abi_output_names":{".class":"SymbolTableNode","kind":"Gdef","node":{".class":"FuncDef","abstract_status":0,"arg_kinds":[0],"arg_names":["abi_element"],"dataclass_transform_spec":null,"deprecated":null,"flags":[],"fullname":"eth_utils.abi.get_abi_output_names","name":"get_abi_output_names","type":{".class":"CallableType","arg_kinds":[0],"arg_names":["abi_element"],"arg_types":[{".class":"TypeAliasType","args":[],"type_ref":"eth_typing.abi.ABIElement"}],"bound_args":[],"def_extras":{"first_arg":null},"fallback":"builtins.function","from_concatenate":false,"implicit":false,"imprecise_arg_kinds":false,"is_ellipsis_args":false,"name":"get_abi_output_names","ret_type":{".class":"Instance","args":["builtins.str"],"extra_attrs":null,"type_ref":"builtins.list"},"type_guard":null,"type_is":null,"unpack_kwargs":false,"variables":[]}}},"get_abi_output_types":{".class":"SymbolTableNode","kind":"Gdef","node":{".class":"FuncDef","abstract_status":0,"arg_kinds":[0],"arg_names":["abi_element"],"dataclass_transform_spec":null,"deprecated":null,"flags":[],"fullname":"eth_utils.abi.get_abi_output_types","name":"get_abi_output_types","type":{".class":"CallableType","arg_kinds":[0],"arg_names":["abi_element"],"arg_types":[{".class":"TypeAliasType","args":[],"type_ref":"eth_typing.abi.ABIElement"}],"bound_args":[],"def_extras":{"first_arg":null},"fallback":"builtins.function","from_concatenate":false,"implicit":false,"imprecise_arg_kinds":false,"is_ellipsis_args":false,"name":"get_abi_output_types","ret_type":{".class":"Instance","args":["builtins.str"],"extra_attrs":null,"type_ref":"builtins.list"},"type_guard":null,"type_is":null,"unpack_kwargs":false,"variables":[]}}},"get_aligned_abi_inputs":{".class":"SymbolTableNode","kind":"Gdef","node":{".class":"FuncDef","abstract_status":0,"arg_kinds":[0,0],"arg_names":["abi_element","normalized_args"],"dataclass_transform_spec":null,"deprecated":null,"flags":[],"fullname":"eth_utils.abi.get_aligned_abi_inputs","name":"get_aligned_abi_inputs","type":{".class":"CallableType","arg_kinds":[0,0],"arg_names":["abi_element","normalized_args"],"arg_types":[{".class":"TypeAliasType","args":[],"type_ref":"eth_typing.abi.ABIElement"},{".class":"UnionType","items":[{".class":"Instance","args":[{".class":"AnyType","missing_import_name":null,"source_any":null,"type_of_any":2}],"extra_attrs":null,"type_ref":"builtins.tuple"},{".class":"Instance","args":[{".class":"AnyType","missing_import_name":null,"source_any":null,"type_of_any":2},{".class":"AnyType","missing_import_name":null,"source_any":null,"type_of_any":2}],"extra_attrs":null,"type_ref":"typing.Mapping"}],"uses_pep604_syntax":false}],"bound_args":[],"def_extras":{"first_arg":null},"fallback":"builtins.function","from_concatenate":false,"implicit":false,"imprecise_arg_kinds":false,"is_ellipsis_args":false,"name":"get_aligned_abi_inputs","ret_type":{".class":"TupleType","implicit":false,"items":[{".class":"Instance","args":["builtins.str"],"extra_attrs":null,"type_ref":"builtins.tuple"},{".class":"Instance","args":[{".class":"AnyType","missing_import_name":null,"source_any":null,"type_of_any":2}],"extra_attrs":null,"type_ref":"builtins.tuple"}],"partial_fallback":{".class":"Instance","args":[{".class":"AnyType","missing_import_name":null,"source_any":null,"type_of_any":6}],"extra_attrs":null,"type_ref":"builtins.tuple"}},"type_guard":null,"type_is":null,"unpack_kwargs":false,"variables":[]}}},"get_all_event_abis":{".class":"SymbolTableNode","kind":"Gdef","node":{".class":"FuncDef","abstract_status":0,"arg_kinds":[0],"arg_names":["contract_abi"],"dataclass_transform_spec":null,"deprecated":null,"flags":[],"fullname":"eth_utils.abi.get_all_event_abis","name":"get_all_event_abis","type":{".class":"CallableType","arg_kinds":[0],"arg_names":["contract_abi"],"arg_types":[{".class":"TypeAliasType","args":[],"type_ref":"eth_typing.abi.ABI"}],"bound_args":[],"def_extras":{"first_arg":null},"fallback":"builtins.function","from_concatenate":false,"implicit":false,"imprecise_arg_kinds":false,"is_ellipsis_args":false,"name":"get_all_event_abis","ret_type":{".class":"Instance","args":[{".class":"TypeAliasType","args":[],"type_ref":"eth_typing.abi.ABIEvent"}],"extra_attrs":null,"type_ref":"typing.Sequence"},"type_guard":null,"type_is":null,"unpack_kwargs":false,"variables":[]}}},"get_all_function_abis":{".class":"SymbolTableNode","kind":"Gdef","node":{".class":"FuncDef","abstract_status":0,"arg_kinds":[0],"arg_names":["contract_abi"],"dataclass_transform_spec":null,"deprecated":null,"flags":[],"fullname":"eth_utils.abi.get_all_function_abis","name":"get_all_function_abis","type":{".class":"CallableType","arg_kinds":[0],"arg_names":["contract_abi"],"arg_types":[{".class":"TypeAliasType","args":[],"type_ref":"eth_typing.abi.ABI"}],"bound_args":[],"def_extras":{"first_arg":null},"fallback":"builtins.function","from_concatenate":false,"implicit":false,"imprecise_arg_kinds":false,"is_ellipsis_args":false,"name":"get_all_function_abis","ret_type":{".class":"Instance","args":[{".class":"TypeAliasType","args":[],"type_ref":"eth_typing.abi.ABIFunction"}],"extra_attrs":null,"type_ref":"typing.Sequence"},"type_guard":null,"type_is":null,"unpack_kwargs":false,"variables":[]}}},"get_normalized_abi_inputs":{".class":"SymbolTableNode","kind":"Gdef","node":{".class":"FuncDef","abstract_status":0,"arg_kinds":[0,2,4],"arg_names":["abi_element","args","kwargs"],"dataclass_transform_spec":null,"deprecated":null,"flags":[],"fullname":"eth_utils.abi.get_normalized_abi_inputs","name":"get_normalized_abi_inputs","type":{".class":"CallableType","arg_kinds":[0,2,4],"arg_names":["abi_element","args","kwargs"],"arg_types":[{".class":"TypeAliasType","args":[],"type_ref":"eth_typing.abi.ABIElement"},{".class":"UnionType","items":[{".class":"Instance","args":[{".class":"AnyType","missing_import_name":null,"source_any":null,"type_of_any":2}],"extra_attrs":null,"type_ref":"typing.Sequence"},{".class":"NoneType"}],"uses_pep604_syntax":false},{".class":"UnionType","items":[{".class":"Instance","args":["builtins.str",{".class":"AnyType","missing_import_name":null,"source_any":null,"type_of_any":2}],"extra_attrs":null,"type_ref":"builtins.dict"},{".class":"NoneType"}],"uses_pep604_syntax":false}],"bound_args":[],"def_extras":{"first_arg":null},"fallback":"builtins.function","from_concatenate":false,"implicit":false,"imprecise_arg_kinds":false,"is_ellipsis_args":false,"name":"get_normalized_abi_inputs","ret_type":{".class":"Instance","args":[{".class":"AnyType","missing_import_name":null,"source_any":null,"type_of_any":2}],"extra_attrs":null,"type_ref":"builtins.tuple"},"type_guard":null,"type_is":null,"unpack_kwargs":false,"variables":[]}}},"is_list_like":{".class":"SymbolTableNode","cross_ref":"eth_utils.types.is_list_like","kind":"Gdef","module_hidden":true,"module_public":false},"itertools":{".class":"SymbolTableNode","cross_ref":"itertools","kind":"Gdef","module_hidden":true,"module_public":false},"keccak":{".class":"SymbolTableNode","cross_ref":"eth_utils.crypto.keccak","kind":"Gdef","module_hidden":true,"module_public":false},"overload":{".class":"SymbolTableNode","cross_ref":"typing.overload","kind":"Gdef","module_hidden":true,"module_public":false},"re":{".class":"SymbolTableNode","cross_ref":"re","kind":"Gdef","module_hidden":true,"module_public":false}},"path":"c:\\Users\\Mr.V\\Documents\\GitHub\\vAIn_p2p_AGI\\.venv\\Lib\\site-packages\\eth_utils\\abi.py"}